scicat/__init__.py
scicat/api.py
scicat/attach.py
scicat/base64_im.py
scicat/download.py
scicat/login.py
scicat/search.py
scicat/upload.py
scicat-1.1.23.dist-info/LICENSE
scicat-1.1.23.dist-info/METADATA
scicat-1.1.23.dist-info/WHEEL
scicat-1.1.23.dist-info/top_level.txt
scicat-1.1.23.dist-info/RECORD
