Metadata-Version: 2.1
Name: scicat
Version: 1.1.23
Summary: a scicat search package
Home-page: https://github.com/garethcmurphy/scicat_pkg
Author: Gareth Murphy
Author-email: garethcmurphy@gmail.com
License: UNKNOWN
Platform: UNKNOWN
Classifier: Programming Language :: Python :: 3
Classifier: License :: OSI Approved :: MIT License
Classifier: Operating System :: OS Independent
Requires-Dist: requests
Requires-Dist: keyring
Requires-Dist: ipywidgets
